agu/__init__.py
agu-0.0.1.dist-info/METADATA
agu-0.0.1.dist-info/WHEEL
agu-0.0.1.dist-info/top_level.txt
agu-0.0.1.dist-info/RECORD
