Metadata-Version: 2.1
Name: agu
Version: 0.0.1
Summary: A stock of China.
Home-page: https://github.com/uliontse/agu
Author: UlionTse
Author-email: shinalone@outlook.com
License: MIT
Keywords: agu,stock
Platform: UNKNOWN
Classifier: Development Status :: 1 - Planning
Classifier: Environment :: Web Environment
Classifier: Intended Audience :: Developers
Classifier: License :: OSI Approved :: MIT License
Classifier: Programming Language :: Python :: 3.5
Classifier: Programming Language :: Python :: 3.6
Classifier: Programming Language :: Python :: 3.7
Classifier: Programming Language :: Python :: 3.8
Requires-Dist: numpy (>=1.19.4)
